wikihowunofficialapi/__init__.py
wikihowunofficialapi/exceptions.py
wikihowunofficialapi-0.1.1.dist-info/LICENSE
wikihowunofficialapi-0.1.1.dist-info/METADATA
wikihowunofficialapi-0.1.1.dist-info/WHEEL
wikihowunofficialapi-0.1.1.dist-info/top_level.txt
wikihowunofficialapi-0.1.1.dist-info/RECORD
