Metadata-Version: 2.1
Name: wikihowunofficialapi
Version: 0.1.1
Summary: API to extract data from wikiHow
Home-page: https://github.com/vigilant-umbrella/wikihowunofficialapi
Author: Aniket Sharma, Ashok Arora
Author-email: vigilant.umbrella@gmail.com
License: MIT
Download-URL: https://github.com/vigilant-umbrella/wikihowunofficialapi/archive/v0.1.1.tar.gz
Platform: UNKNOWN
Classifier: Intended Audience :: Science/Research
Classifier: License :: OSI Approved :: MIT License
Classifier: Operating System :: OS Independent
Classifier: Programming Language :: Python :: 3
Requires-Python: >=3.6
Requires-Dist: bs4
Requires-Dist: tqdm
